heaven_tree_repl/__init__.py
heaven_tree_repl/agent_config_management.py
heaven_tree_repl/agent_management.py
heaven_tree_repl/approval_system.py
heaven_tree_repl/base.py
heaven_tree_repl/category_theory.py
heaven_tree_repl/cli.py
heaven_tree_repl/command_handlers.py
heaven_tree_repl/config_models.py
heaven_tree_repl/conversation_chat_app.py
heaven_tree_repl/display_brief.py
heaven_tree_repl/execution_engine.py
heaven_tree_repl/library_factory.py
heaven_tree_repl/logger.py
heaven_tree_repl/meta_operations.py
heaven_tree_repl/ontology_primitives.py
heaven_tree_repl/pathway_management.py
heaven_tree_repl/recursive_factory.py
heaven_tree_repl/renderer.py
heaven_tree_repl/rsi_analysis.py
heaven_tree_repl/run_user_tree_shell.py
heaven_tree_repl/shells.py
heaven_tree_repl/system_config_loader.py
heaven_tree_repl/system_config_loader_v2.py
heaven_tree_repl/tool_generator.py
heaven_tree_repl/tools.py
heaven_tree_repl/visualization_utils.py
heaven_tree_repl/mcp_generator/__init__.py
heaven_tree_repl/mcp_generator/config.py
heaven_tree_repl/mcp_generator/generator.py
heaven_tree_repl/mcp_server/__init__.py
heaven_tree_repl/mcp_server/__main__.py
heaven_tree_repl/mcp_server/server.py
heaven_tree_repl-0.1.38.dist-info/licenses/LICENSE
mcp_server/__init__.py
mcp_server/__main__.py
mcp_server/server.py
mcp_server/test_server.py
mcp_server/test_simple_server.py
heaven_tree_repl-0.1.38.dist-info/METADATA
heaven_tree_repl-0.1.38.dist-info/WHEEL
heaven_tree_repl-0.1.38.dist-info/entry_points.txt
heaven_tree_repl-0.1.38.dist-info/top_level.txt
heaven_tree_repl-0.1.38.dist-info/RECORD
