Metadata-Version: 2.4
Name: heaven-tree-repl
Version: 0.1.38
Summary: Hierarchical Embodied Autonomously Validating Evolution Network Tree REPL
Home-page: https://github.com/yourusername/heaven-tree-repl
Author: HEAVEN Development Team
Author-email: HEAVEN Development Team <heaven@example.com>
License: MIT
Project-URL: Homepage, https://github.com/yourusername/heaven-tree-repl
Project-URL: Repository, https://github.com/yourusername/heaven-tree-repl
Project-URL: Issues, https://github.com/yourusername/heaven-tree-repl/issues
Classifier: Development Status :: 3 - Alpha
Classifier: Intended Audience :: Developers
Classifier: License :: OSI Approved :: MIT License
Classifier: Operating System :: OS Independent
Classifier: Programming Language :: Python :: 3
Classifier: Programming Language :: Python :: 3.8
Classifier: Programming Language :: Python :: 3.9
Classifier: Programming Language :: Python :: 3.10
Classifier: Programming Language :: Python :: 3.11
Requires-Python: >=3.8
License-File: LICENSE
Requires-Dist: pydantic>=2.0.0
Requires-Dist: jinja2>=3.0.0
Provides-Extra: dev
Requires-Dist: pytest>=6.0; extra == "dev"
Requires-Dist: black; extra == "dev"
Requires-Dist: flake8; extra == "dev"
Requires-Dist: mypy; extra == "dev"
Dynamic: author
Dynamic: home-page
Dynamic: license-file
Dynamic: requires-python
